{
  "db_name": "SQLite",
  "query": "\n        SELECT *\n        FROM tags\n        ORDER BY tags.value ASC\n    ",
  "describe": {
    "columns": [
      {
        "name": "id",
        "ordinal": 0,
        "type_info": "Integer"
      },
      {
        "name": "value",
        "ordinal": 1,
        "type_info": "Text"
      }
    ],
    "parameters": {
      "Right": 0
    },
    "nullable": [
      false,
      false
    ]
  },
  "hash": "932f1d26dfda8ade96a31e23a3164944065535339bf5fb9d112d65dccc131058"
}
